{".class": "MypyFile", "_fullname": "groups.views", "is_partial_stub_package": false, "is_stub": false, "names": {".class": "SymbolTable", "CreateGroup": {".class": "SymbolTableNode", "kind": "Gdef", "node": {".class": "TypeInfo", "_promote": null, "abstract_attributes": [], "bases": ["builtins.object"], "declared_metaclass": null, "defn": {".class": "ClassDef", "fullname": "groups.views.CreateGroup", "name": "CreateGroup", "type_vars": []}, "flags": ["fallback_to_any"], "fullname": "groups.views.CreateGroup", "metaclass_type": null, "metadata": {}, "module_name": "groups.views", "mro": ["groups.views.CreateGroup", "builtins.object"], "names": {".class": "SymbolTable", "fields": {".class": "SymbolTableNode", "kind": "Mdef", "node": {".class": "Var", "flags": ["is_initialized_in_class"], "fullname": "groups.views.CreateGroup.fields", "name": "fields", "type": {".class": "TupleType", "implicit": false, "items": ["builtins.str", "builtins.str"], "partial_fallback": {".class": "Instance", "args": [{".class": "AnyType", "missing_import_name": null, "source_any": null, "type_of_any": 6}], "type_ref": "builtins.tuple"}}}}, "model": {".class": "SymbolTableNode", "kind": "Mdef", "node": {".class": "Var", "flags": ["is_initialized_in_class"], "fullname": "groups.views.CreateGroup.model", "name": "model", "type": {".class": "CallableType", "arg_kinds": [2, 4], "arg_names": ["_args", "_kwds"], "arg_types": [{".class": "AnyType", "missing_import_name": null, "source_any": null, "type_of_any": 6}, {".class": "AnyType", "missing_import_name": null, "source_any": null, "type_of_any": 6}], "bound_args": [], "def_extras": {}, "fallback": "builtins.type", "implicit": false, "is_ellipsis_args": false, "name": null, "ret_type": "groups.models.Group", "variables": []}}}}, "tuple_type": null, "type_vars": [], "typeddict_type": null}}, "Group": {".class": "SymbolTableNode", "cross_ref": "groups.models.Group", "kind": "Gdef"}, "GroupMember": {".class": "SymbolTableNode", "cross_ref": "groups.models.GroupMember", "kind": "Gdef"}, "IntegrityError": {".class": "SymbolTableNode", "kind": "Gdef", "node": {".class": "Var", "flags": ["is_suppressed_import", "is_ready"], "fullname": "groups.views.IntegrityError", "name": "IntegrityError", "type": {".class": "AnyType", "missing_import_name": "groups.views.IntegrityError", "source_any": null, "type_of_any": 3}}}, "JoinGroup": {".class": "SymbolTableNode", "kind": "Gdef", "node": {".class": "TypeInfo", "_promote": null, "abstract_attributes": [], "bases": ["builtins.object"], "declared_metaclass": null, "defn": {".class": "ClassDef", "fullname": "groups.views.JoinGroup", "name": "JoinGroup", "type_vars": []}, "flags": ["fallback_to_any"], "fullname": "groups.views.JoinGroup", "metaclass_type": null, "metadata": {}, "module_name": "groups.views", "mro": ["groups.views.JoinGroup", "builtins.object"], "names": {".class": "SymbolTable", "get": {".class": "SymbolTableNode", "kind": "Mdef", "node": {".class": "FuncDef", "arg_kinds": [0, 0, 2, 4], "arg_names": ["self", "request", "args", "kwargs"], "flags": [], "fullname": "groups.views.JoinGroup.get", "name": "get", "type": null}}, "get_redirect_url": {".class": "SymbolTableNode", "kind": "Mdef", "node": {".class": "FuncDef", "arg_kinds": [0, 2, 4], "arg_names": ["self", "args", "kwargs"], "flags": [], "fullname": "groups.views.JoinGroup.get_redirect_url", "name": "get_redirect_url", "type": null}}}, "tuple_type": null, "type_vars": [], "typeddict_type": null}}, "LeaveGroup": {".class": "SymbolTableNode", "kind": "Gdef", "node": {".class": "TypeInfo", "_promote": null, "abstract_attributes": [], "bases": ["builtins.object"], "declared_metaclass": null, "defn": {".class": "ClassDef", "fullname": "groups.views.LeaveGroup", "name": "LeaveGroup", "type_vars": []}, "flags": ["fallback_to_any"], "fullname": "groups.views.LeaveGroup", "metaclass_type": null, "metadata": {}, "module_name": "groups.views", "mro": ["groups.views.LeaveGroup", "builtins.object"], "names": {".class": "SymbolTable", "get": {".class": "SymbolTableNode", "kind": "Mdef", "node": {".class": "FuncDef", "arg_kinds": [0, 0, 2, 4], "arg_names": ["self", "request", "args", "kwargs"], "flags": [], "fullname": "groups.views.LeaveGroup.get", "name": "get", "type": null}}, "get_redirect_url": {".class": "SymbolTableNode", "kind": "Mdef", "node": {".class": "FuncDef", "arg_kinds": [0, 2, 4], "arg_names": ["self", "args", "kwargs"], "flags": [], "fullname": "groups.views.LeaveGroup.get_redirect_url", "name": "get_redirect_url", "type": null}}}, "tuple_type": null, "type_vars": [], "typeddict_type": null}}, "ListGroups": {".class": "SymbolTableNode", "kind": "Gdef", "node": {".class": "TypeInfo", "_promote": null, "abstract_attributes": [], "bases": ["builtins.object"], "declared_metaclass": null, "defn": {".class": "ClassDef", "fullname": "groups.views.ListGroups", "name": "ListGroups", "type_vars": []}, "flags": ["fallback_to_any"], "fullname": "groups.views.ListGroups", "metaclass_type": null, "metadata": {}, "module_name": "groups.views", "mro": ["groups.views.ListGroups", "builtins.object"], "names": {".class": "SymbolTable", "model": {".class": "SymbolTableNode", "kind": "Mdef", "node": {".class": "Var", "flags": ["is_initialized_in_class"], "fullname": "groups.views.ListGroups.model", "name": "model", "type": {".class": "CallableType", "arg_kinds": [2, 4], "arg_names": ["_args", "_kwds"], "arg_types": [{".class": "AnyType", "missing_import_name": null, "source_any": null, "type_of_any": 6}, {".class": "AnyType", "missing_import_name": null, "source_any": null, "type_of_any": 6}], "bound_args": [], "def_extras": {}, "fallback": "builtins.type", "implicit": false, "is_ellipsis_args": false, "name": null, "ret_type": "groups.models.Group", "variables": []}}}}, "tuple_type": null, "type_vars": [], "typeddict_type": null}}, "LoginRequiredMixin": {".class": "SymbolTableNode", "kind": "Gdef", "node": {".class": "Var", "flags": ["is_suppressed_import", "is_ready"], "fullname": "groups.views.LoginRequiredMixin", "name": "LoginRequiredMixin", "type": {".class": "AnyType", "missing_import_name": "groups.views.LoginRequiredMixin", "source_any": null, "type_of_any": 3}}}, "PermissionRequiredMixin": {".class": "SymbolTableNode", "kind": "Gdef", "node": {".class": "Var", "flags": ["is_suppressed_import", "is_ready"], "fullname": "groups.views.PermissionRequiredMixin", "name": "PermissionRequiredMixin", "type": {".class": "AnyType", "missing_import_name": "groups.views.PermissionRequiredMixin", "source_any": null, "type_of_any": 3}}}, "SingleGroup": {".class": "SymbolTableNode", "kind": "Gdef", "node": {".class": "TypeInfo", "_promote": null, "abstract_attributes": [], "bases": ["builtins.object"], "declared_metaclass": null, "defn": {".class": "ClassDef", "fullname": "groups.views.SingleGroup", "name": "SingleGroup", "type_vars": []}, "flags": ["fallback_to_any"], "fullname": "groups.views.SingleGroup", "metaclass_type": null, "metadata": {}, "module_name": "groups.views", "mro": ["groups.views.SingleGroup", "builtins.object"], "names": {".class": "SymbolTable", "model": {".class": "SymbolTableNode", "kind": "Mdef", "node": {".class": "Var", "flags": ["is_initialized_in_class"], "fullname": "groups.views.SingleGroup.model", "name": "model", "type": {".class": "CallableType", "arg_kinds": [2, 4], "arg_names": ["_args", "_kwds"], "arg_types": [{".class": "AnyType", "missing_import_name": null, "source_any": null, "type_of_any": 6}, {".class": "AnyType", "missing_import_name": null, "source_any": null, "type_of_any": 6}], "bound_args": [], "def_extras": {}, "fallback": "builtins.type", "implicit": false, "is_ellipsis_args": false, "name": null, "ret_type": "groups.models.Group", "variables": []}}}}, "tuple_type": null, "type_vars": [], "typeddict_type": null}}, "__doc__": {".class": "SymbolTableNode", "kind": "Gdef", "node": {".class": "Var", "flags": ["is_ready"], "fullname": "groups.views.__doc__", "name": "__doc__", "type": "builtins.str"}}, "__file__": {".class": "SymbolTableNode", "kind": "Gdef", "node": {".class": "Var", "flags": ["is_ready"], "fullname": "groups.views.__file__", "name": "__file__", "type": "builtins.str"}}, "__name__": {".class": "SymbolTableNode", "kind": "Gdef", "node": {".class": "Var", "flags": ["is_ready"], "fullname": "groups.views.__name__", "name": "__name__", "type": "builtins.str"}}, "__package__": {".class": "SymbolTableNode", "kind": "Gdef", "node": {".class": "Var", "flags": ["is_ready"], "fullname": "groups.views.__package__", "name": "__package__", "type": "builtins.str"}}, "generic": {".class": "SymbolTableNode", "kind": "Gdef", "node": {".class": "Var", "flags": ["is_suppressed_import", "is_ready"], "fullname": "groups.views.generic", "name": "generic", "type": {".class": "AnyType", "missing_import_name": "groups.views.generic", "source_any": null, "type_of_any": 3}}}, "get_object_or_404": {".class": "SymbolTableNode", "kind": "Gdef", "node": {".class": "Var", "flags": ["is_suppressed_import", "is_ready"], "fullname": "groups.views.get_object_or_404", "name": "get_object_or_404", "type": {".class": "AnyType", "missing_import_name": "groups.views.get_object_or_404", "source_any": null, "type_of_any": 3}}}, "messages": {".class": "SymbolTableNode", "kind": "Gdef", "node": {".class": "Var", "flags": ["is_suppressed_import", "is_ready"], "fullname": "groups.views.messages", "name": "messages", "type": {".class": "AnyType", "missing_import_name": "groups.views.messages", "source_any": null, "type_of_any": 3}}}, "models": {".class": "SymbolTableNode", "cross_ref": "groups.models", "kind": "Gdef"}, "reverse": {".class": "SymbolTableNode", "kind": "Gdef", "node": {".class": "Var", "flags": ["is_suppressed_import", "is_ready"], "fullname": "groups.views.reverse", "name": "reverse", "type": {".class": "AnyType", "missing_import_name": "groups.views.reverse", "source_any": null, "type_of_any": 3}}}}, "path": "c:\\Users\\user\\Desktop\\simple_social_clone\\simplesocial\\groups\\views.py"}